{
  "hash": "eb5bbc8fc39d51871ff677fe1bc0c5d2",
  "result": {
    "engine": "knitr",
    "markdown": "---\ntitle: \"About\"\ntoc: false\n---\n\n\n\n\n\n## Heading 2\n\nAbout this site\n\n\n\n\n::: {.cell}\n\n```{.r .cell-code}\n1 + 3\n```\n\n::: {.cell-output .cell-output-stdout}\n\n```\n[1] 4\n```\n\n\n:::\n:::\n\n::: {.cell}\n\n```{.r .cell-code}\nrunif(10)\n```\n\n::: {.cell-output .cell-output-stdout}\n\n```\n [1] 0.5193916 0.2871750 0.8395306 0.9112439 0.6903794 0.1335740 0.2522363\n [8] 0.5253886 0.2336891 0.8581399\n```\n\n\n:::\n:::\n\n\n\n\n\n\n\n### Heading 3\n\n\n## New Heading 2",
    "supporting": [],
    "filters": [
      "rmarkdown/pagebreak.lua"
    ],
    "includes": {},
    "engineDependencies": {},
    "preserve": {},
    "postProcess": true
  }
}